{"per_page":10,"total":6,"current":4,"data":[{"title":"PAT basic level 1002","date":"2019-04-10T09:04:21.000Z","excerpt":"<p>PAT basic level 1002 写出这个数<br></p>","link":"2019/04/10/PAT basic/1002","tags":["PAT basic"],"categories":["PAT basic"]},{"title":"PAT basic level 1010","date":"2019-04-10T09:04:21.000Z","excerpt":"<p>PAT basic level 1010  一元多项式求导<br></p>","link":"2019/04/10/PAT basic/PAT (Basic Level) Practice  1010","tags":["PAT basic"],"categories":["PAT basic"]},{"title":"PAT basic level 1004","date":"2019-04-10T09:04:21.000Z","excerpt":"<p>PAT basic level 1004  成绩排名<br></p>","link":"2019/04/10/PAT basic/PAT (Basic Level) Practice  1004","tags":["PAT basic"],"categories":["PAT basic"]},{"title":"PAT basic level 1015","date":"2019-04-10T09:04:21.000Z","excerpt":"<p>PAT basic level 1015  德才论<br></p>","link":"2019/04/10/PAT basic/PAT (Basic Level) Practice  1015","tags":["PAT basic"],"categories":["PAT basic"]},{"title":"PAT basic level 1012","date":"2019-04-10T09:04:21.000Z","excerpt":"<p>PAT basic level 1012  数字分类<br></p>","link":"2019/04/10/PAT basic/PAT (Basic Level) Practice  1012","tags":["PAT basic"],"categories":["PAT basic"]},{"title":"PAT basic level 1013","date":"2019-04-10T09:04:21.000Z","excerpt":"<p>PAT basic level 1013 数素数<br></p>","link":"2019/04/10/PAT basic/PAT (Basic Level) Practice  1013","tags":["PAT basic"],"categories":["PAT basic"]},{"title":"PAT basic level 1009","date":"2019-04-10T09:04:21.000Z","excerpt":"<p>PAT basic level 1009  说反话<br></p>","link":"2019/04/10/PAT basic/PAT (Basic Level) Practice  1009","tags":["PAT basic"],"categories":["PAT basic"]},{"title":"PAT basic level 1018","date":"2019-04-10T09:04:21.000Z","excerpt":"<p>PAT basic level 1018  锤子剪刀布图<br></p>","link":"2019/04/10/PAT basic/PAT (Basic Level) Practice  1018","tags":["PAT basic"],"categories":["PAT basic"]},{"title":"PAT basic level 1001","date":"2019-04-10T09:04:21.000Z","excerpt":"<p>PAT basic level 1001  害死人不偿命的(3n+1)猜想<br></p>","link":"2019/04/10/PAT basic/PAT-basic-level-1001","tags":["PAT basic"],"categories":["PAT basic"]},{"title":"PAT basic level 1006","date":"2019-04-10T09:04:21.000Z","excerpt":"<p>PAT basic level 1006  换个格式输出整数<br></p>","link":"2019/04/10/PAT basic/PAT (Basic Level) Practice  1006","tags":["PAT basic"],"categories":["PAT basic"]}]}